MANIFEST.in
README.rst
setup.py
Products/__init__.py
Products.ZServerViews.egg-info/PKG-INFO
Products.ZServerViews.egg-info/SOURCES.txt
Products.ZServerViews.egg-info/dependency_links.txt
Products.ZServerViews.egg-info/namespace_packages.txt
Products.ZServerViews.egg-info/not-zip-safe
Products.ZServerViews.egg-info/requires.txt
Products.ZServerViews.egg-info/top_level.txt
Products/ZServerViews/__init__.py
Products/ZServerViews/base.py
Products/ZServerViews/handler.py
Products/ZServerViews/version.txt
Products/ZServerViews/tests/__init__.py
Products/ZServerViews/tests/common.py
Products/ZServerViews/tests/test_configuration.py
Products/ZServerViews/tests/test_zserver_views.py
docs/HISTORY.txt