Metadata-Version: 1.0
Name: Products.ZServerViews
Version: 0.2.0
Summary: Provide infrastructure for plugging views that run directly at the ZServer
Home-page: http://pypi.python.org/pypi/Products.ZServerViews
Author: Leonardo Rochael Almeida
Author-email: leorochael@gmail.com
License: ZPL
Keywords: zope2 plone
Platform: UNKNOWN
Classifier: Programming Language :: Python
Classifier: Framework :: Zope2
Classifier: Intended Audience :: System Administrators
